yuyo/__init__.py
yuyo/__main__.py
yuyo/asgi.py
yuyo/backoff.py
yuyo/chunk_tracker.py
yuyo/components.py
yuyo/interactions.py
yuyo/links.py
yuyo/list_status.py
yuyo/modals.py
yuyo/pagination.py
yuyo/py.typed
yuyo/reactions.py
yuyo/timeouts.py
yuyo/to_builder.py
yuyo/_internal/__init__.py
yuyo/_internal/localise.py
yuyo/_internal/vendor/__init__.py
yuyo/_internal/vendor/inspect.py
yuyo/_internal/vendor/inspect.py.LICENSE
yuyo/_internal/vendor/inspect.pyi
yuyo/_internal/vendor/inspect.pyi.LICENSE
hikari_yuyo-1.23.1.dist-info/entry_points.txt
hikari_yuyo-1.23.1.dist-info/LICENSE
hikari_yuyo-1.23.1.dist-info/WHEEL
hikari_yuyo-1.23.1.dist-info/METADATA
hikari_yuyo-1.23.1.dist-info/RECORD
