Metadata-Version: 2.1
Name: hikari-yuyo
Version: 1.23.1
Summary: A collection of utility functions and classes designed to expand Hikari.
Keywords: hikari
Author-email: Faster Speeding <lucina@lmbyrne.dev>
Requires-Python: >=3.9.0,<3.14
Classifier: Development Status :: 5 - Production/Stable
Classifier: License :: OSI Approved :: BSD License
Classifier: Intended Audience :: Developers
Classifier: Natural Language :: English
Classifier: Operating System :: OS Independent
Classifier: Programming Language :: Python :: 3.9
Classifier: Programming Language :: Python :: 3.10
Classifier: Programming Language :: Python :: 3.11
Classifier: Programming Language :: Python :: 3.12
Classifier: Programming Language :: Python :: 3.13
Classifier: Programming Language :: Python :: Implementation :: CPython
Classifier: Topic :: Communications :: Chat
Classifier: Topic :: Software Development :: Libraries
Classifier: Topic :: Software Development :: Libraries :: Python Modules
Classifier: Topic :: Utilities
Classifier: Typing :: Typed
Requires-Dist: alluka>=0.2.0, <1
Requires-Dist: hikari>=2.0.0.dev118, <3
Requires-Dist: typing_extensions>=4.5
Requires-Dist: asgiref~=3.0 ; extra == "asgi"
Requires-Dist: hikari[server] ; extra == "asgi"
Requires-Dist: click>=8, <9 ; extra == "cli"
Requires-Dist: pydantic>=2, <3 ; extra == "cli"
Requires-Dist: python-dotenv>=1, <2 ; extra == "cli"
Requires-Dist: toml>=0.10, <1 ; extra == "cli"
Requires-Dist: hikari-sake>=1.0.4a1, <2 ; extra == "sake"
Requires-Dist: hikari-tanjun>=2.11.0, <3 ; extra == "tanjun"
Project-URL: Changelog, https://yuyo.cursed.solutions/changelog
Project-URL: Documentation, https://yuyo.cursed.solutions/
Project-URL: Homepage, https://github.com/FasterSpeeding/Yuyo
Project-URL: Repository, https://github.com/FasterSpeeding/Yuyo
Provides-Extra: asgi
Provides-Extra: cli
Provides-Extra: sake
Provides-Extra: tanjun
